pipedrive/__init__.py
pipedrive/activities.py
pipedrive/client.py
pipedrive/deals.py
pipedrive/exceptions.py
pipedrive/filters.py
pipedrive/items.py
pipedrive/leads.py
pipedrive/notes.py
pipedrive/organizations.py
pipedrive/persons.py
pipedrive/pipelines.py
pipedrive/products.py
pipedrive/recents.py
pipedrive/stages.py
pipedrive/subscriptions.py
pipedrive/users.py
pipedrive/webhooks.py
pipedrive_python_lib-1.2.2.dist-info/LICENSE
pipedrive_python_lib-1.2.2.dist-info/METADATA
pipedrive_python_lib-1.2.2.dist-info/WHEEL
pipedrive_python_lib-1.2.2.dist-info/RECORD
